simpn/__init__.py
simpn/analysis.py
simpn/assets.py
simpn/bpmn_parser.py
simpn/immutabletypes.py
simpn/priorities.py
simpn/prototypes.py
simpn/prototypes_queueing.py
simpn/reporters.py
simpn/simulator.py
simpn/utils.py
simpn/assets/SimPN.icns
simpn/assets/SimPN.ico
simpn/assets/img/clear.png
simpn/assets/img/clock.png
simpn/assets/img/close.png
simpn/assets/img/faster.png
simpn/assets/img/flip_close.png
simpn/assets/img/flip_open.png
simpn/assets/img/ide_faster.png
simpn/assets/img/ide_play.png
simpn/assets/img/ide_slower.png
simpn/assets/img/ide_step.png
simpn/assets/img/ide_stop.png
simpn/assets/img/logo.png
simpn/assets/img/minus.png
simpn/assets/img/open.png
simpn/assets/img/play.png
simpn/assets/img/plus.png
simpn/assets/img/slower.png
simpn/assets/img/step.png
simpn/assets/img/stop.png
simpn/assets/img/time_back.png
simpn/assets/img/zoom-in.png
simpn/assets/img/zoom-out.png
simpn/assets/img/zoom-reset.png
simpn/helpers/__init__.py
simpn/helpers/bpmn.py
simpn/helpers/petrinets.py
simpn/visualisation/__init__.py
simpn/visualisation/base.py
simpn/visualisation/constants.py
simpn/visualisation/events.py
simpn/visualisation/model_panel.py
simpn/visualisation/model_panel_mods.py
simpn/visualisation/text.py
simpn-1.7.10.dist-info/METADATA
simpn-1.7.10.dist-info/WHEEL
simpn-1.7.10.dist-info/licenses/LICENSE
simpn-1.7.10.dist-info/RECORD
