Metadata-Version: 2.4
Name: simpn
Version: 1.7.10
Summary: A package for Discrete Event Simulation, using the theory of Petri Nets.
Project-URL: Homepage, https://github.com/bpogroup/simpn
Project-URL: Documentation, https://bpogroup.github.io/simpn/
Author-email: Remco Dijkman <r.m.dijkman@tue.nl>
License: Copyright (c) 2023 Remco Dijkman (Eindhoven University of Technology)
License-File: LICENSE
Classifier: License :: OSI Approved :: MIT License
Classifier: Operating System :: OS Independent
Classifier: Programming Language :: Python :: 3
Requires-Python: >=3.9
Requires-Dist: igraph>=1.0.0
Requires-Dist: imageio>=2.7
Requires-Dist: matplotlib>=3.9.3
Requires-Dist: pygame>=2.6.1
Requires-Dist: pyqt6>=6.9.1
Requires-Dist: python-igraph>=1.0.0
Requires-Dist: sortedcontainers>=2.4.0
Provides-Extra: dev
Requires-Dist: numpy; extra == 'dev'
